CONTRIBUTORS.txt
COPYING
COPYING.LESSER
MANIFEST.in
README.rst
README_short.rst
VERSION.txt
dev_requirements.txt
pyproject.toml
requirements.txt
setup.py
whichcraft.py
SEAScope/__init__.py
SEAScope/flatbuffers1_compat.py
SEAScope/upload.py
SEAScope/API/AddCollection.py
SEAScope/API/AddGranule.py
SEAScope/API/AddSource.py
SEAScope/API/AddTimespan.py
SEAScope/API/AddTimestep.py
SEAScope/API/AddVariable.py
SEAScope/API/BasicResponse.py
SEAScope/API/CheckSchemaVersion.py
SEAScope/API/CheckSchemaVersionResponse.py
SEAScope/API/Collection.py
SEAScope/API/CollectionId.py
SEAScope/API/Color.py
SEAScope/API/Command.py
SEAScope/API/CommandArgs.py
SEAScope/API/DataBucket.py
SEAScope/API/DataInfo.py
SEAScope/API/DataModel.py
SEAScope/API/DataType.py
SEAScope/API/Extraction.py
SEAScope/API/FilterMode.py
SEAScope/API/FloatDataBucket.py
SEAScope/API/GCP.py
SEAScope/API/GetCataloguesResponse.py
SEAScope/API/GetCurrentDatetimeResponse.py
SEAScope/API/GetDataAlwaysVisibleModeResponse.py
SEAScope/API/GetExtractionResponse.py
SEAScope/API/GetNearestModeResponse.py
SEAScope/API/GetRendering.py
SEAScope/API/GetRenderingResponse.py
SEAScope/API/GetTimespanResponse.py
SEAScope/API/GetTimestepResponse.py
SEAScope/API/GetVariableIdentifier.py
SEAScope/API/GetVariableIdentifierResponse.py
SEAScope/API/Granule.py
SEAScope/API/GranuleData.py
SEAScope/API/GranuleId.py
SEAScope/API/GranuleMetadata.py
SEAScope/API/IDFDescriptor.py
SEAScope/API/ListCollectionsResponse.py
SEAScope/API/ListSourcesResponse.py
SEAScope/API/ListTimespansResponse.py
SEAScope/API/ListTimestepsResponse.py
SEAScope/API/ListVariablesResponse.py
SEAScope/API/ListVisibleDataResponse.py
SEAScope/API/LookAt.py
SEAScope/API/OpCode.py
SEAScope/API/RemoveCollection.py
SEAScope/API/RemoveSource.py
SEAScope/API/RemoveTimespan.py
SEAScope/API/RemoveTimestep.py
SEAScope/API/RemoveVariable.py
SEAScope/API/RenderableId.py
SEAScope/API/RenderingCfg.py
SEAScope/API/RenderingMethod.py
SEAScope/API/SearchGranules.py
pySEAScope.egg-info/PKG-INFO
pySEAScope.egg-info/SOURCES.txt
pySEAScope.egg-info/dependency_links.txt
pySEAScope.egg-info/entry_points.txt
pySEAScope.egg-info/not-zip-safe
pySEAScope.egg-info/requires.txt
pySEAScope.egg-info/top_level.txt
