Metadata-Version: 2.2
Name: pySEAScope
Version: 0.3.229
Summary: Python bindings to interact with the SEAScope application
Home-page: https://seascope.oceandatalab.com/python.html
Author: ('Sylvain Herlédan <sylvain.herledan@oceandatalab.com',)
Author-email: seascope@oceandatalab.com
Maintainer: ('Sylvain Herlédan <sylvain.herledan@oceandatalab.com',)
Maintainer-email: seascope@oceandatalab.com
License: COPYING.LESSER
Classifier: Development Status :: 4 - Beta
Classifier: Environment :: Console
Classifier: Intended Audience :: Developers
Classifier: Intended Audience :: Education
Classifier: Intended Audience :: End Users/Desktop
Classifier: Intended Audience :: Science/Research
Classifier: Operating System :: POSIX :: Linux
Classifier: Operating System :: MacOS :: MacOS X
Classifier: Operating System :: Microsoft :: Windows :: Windows 10
Classifier: Operating System :: Microsoft :: Windows :: Windows 8.1
Classifier: Operating System :: Microsoft :: Windows :: Windows 8
Classifier: Operating System :: Microsoft :: Windows :: Windows 7
Classifier: Programming Language :: Python :: 3.7
Classifier: Topic :: Scientific/Engineering
Classifier: Topic :: Scientific/Engineering :: Visualization
Classifier: Topic :: Scientific/Engineering :: GIS
License-File: COPYING
License-File: COPYING.LESSER
Requires-Dist: flatbuffers<2.0
Provides-Extra: processor
Requires-Dist: matplotlib; extra == "processor"
Requires-Dist: numpy; extra == "processor"
Requires-Dist: pyproj; extra == "processor"
Provides-Extra: doc
Requires-Dist: sphinx; extra == "doc"
Dynamic: author
Dynamic: author-email
Dynamic: classifier
Dynamic: description
Dynamic: description-content-type
Dynamic: home-page
Dynamic: license
Dynamic: maintainer
Dynamic: maintainer-email
Dynamic: provides-extra
Dynamic: requires-dist
Dynamic: summary
